aaki/__init__.py
aaki/comma_corrector/__init__.py
aaki/comma_corrector/comma_corrector.py
aaki/comma_corrector/comma_tester.py
aaki/comma_corrector/rules.py
tests/__init__.py
tests/test_comma_corrector/__init__.py
tests/test_comma_corrector/test_comma_corrector.py
tests/test_comma_corrector/test_rules/__init__.py
tests/test_comma_corrector/test_rules/test_a.py
tests/test_comma_corrector/test_rules/test_aby.py
tests/test_comma_corrector/test_rules/test_albo.py
tests/test_comma_corrector/test_rules/test_ale.py
tests/test_comma_corrector/test_rules/test_ani.py
tests/test_comma_corrector/test_rules/test_aż.py
tests/test_comma_corrector/test_rules/test_bo.py
tests/test_comma_corrector/test_rules/test_bowiem.py
tests/test_comma_corrector/test_rules/test_by.py
tests/test_comma_corrector/test_rules/test_bądź.py
tests/test_comma_corrector/test_rules/test_chociaż.py
tests/test_comma_corrector/test_rules/test_choć.py
tests/test_comma_corrector/test_rules/test_co.py
tests/test_comma_corrector/test_rules/test_czy.py
tests/test_comma_corrector/test_rules/test_czyli.py
tests/test_comma_corrector/test_rules/test_dlatego.py
tests/test_comma_corrector/test_rules/test_dopóki.py
tests/test_comma_corrector/test_rules/test_gdy.py
tests/test_comma_corrector/test_rules/test_gdyż.py
tests/test_comma_corrector/test_rules/test_gdzie.py
tests/test_comma_corrector/test_rules/test_i.py
tests/test_comma_corrector/test_rules/test_inne.py
tests/test_comma_corrector/test_rules/test_iż.py
tests/test_comma_corrector/test_rules/test_jak.py
tests/test_comma_corrector/test_rules/test_jakby.py
tests/test_comma_corrector/test_rules/test_jako.py
tests/test_comma_corrector/test_rules/test_jednak.py
tests/test_comma_corrector/test_rules/test_jeśli.py
tests/test_comma_corrector/test_rules/test_jeżeli.py
tests/test_comma_corrector/test_rules/test_kiedy.py
tests/test_comma_corrector/test_rules/test_który.py
tests/test_comma_corrector/test_rules/test_lecz.py
tests/test_comma_corrector/test_rules/test_lub.py
aaki-0.3.0.dist-info/METADATA
aaki-0.3.0.dist-info/WHEEL
aaki-0.3.0.dist-info/top_level.txt
aaki-0.3.0.dist-info/RECORD
