Metadata-Version: 2.1
Name: aaki
Version: 0.3.0
Summary: UNKNOWN
Home-page: UNKNOWN
License: UNKNOWN
Platform: UNKNOWN
Requires-Dist: pytest
Requires-Dist: spacy
